singularity/__init__.py
singularity/__version__.py
singularity/api.py
singularity/exceptions.py
singularity_energy-0.0.9.dist-info/METADATA
singularity_energy-0.0.9.dist-info/WHEEL
singularity_energy-0.0.9.dist-info/top_level.txt
singularity_energy-0.0.9.dist-info/RECORD
